{"stats":{"minecraft:custom":{"minecraft:interact_with_crafting_table":1,"minecraft:sprint_one_cm":4530,"minecraft:time_since_rest":2714,"minecraft:fall_one_cm":3117,"minecraft:walk_one_cm":3828,"minecraft:total_world_time":2714,"minecraft:leave_game":1,"minecraft:fly_one_cm":4870,"minecraft:damage_taken":30,"minecraft:play_time":2714,"minecraft:jump":40,"minecraft:time_since_death":2714},"minecraft:crafted":{"minecraft:stick":4,"minecraft:spruce_planks":28,"minecraft:crafting_table":1},"minecraft:picked_up":{"minecraft:spruce_log":7},"minecraft:used":{"minecraft:crafting_table":1},"minecraft:mined":{"minecraft:spruce_log":7}},"DataVersion":4325}